diffdrr/__init__.py
diffdrr/_modidx.py
diffdrr/data.py
diffdrr/detector.py
diffdrr/drr.py
diffdrr/metrics.py
diffdrr/pose.py
diffdrr/registration.py
diffdrr/renderers.py
diffdrr/utils.py
diffdrr/visualization.py
diffdrr/data/cxr.nii.gz
diffdrr/data/mask.nii.gz
diffdrr/data/structures.csv
diffdrr-0.6.0.dist-info/LICENSE
diffdrr-0.6.0.dist-info/METADATA
diffdrr-0.6.0.dist-info/WHEEL
diffdrr-0.6.0.dist-info/entry_points.txt
diffdrr-0.6.0.dist-info/top_level.txt
diffdrr-0.6.0.dist-info/RECORD
