Metadata-Version: 2.1
Name: diffdrr
Version: 0.6.0
Summary: Auto-differentiable digitally reconstructed radiographs in PyTorch
Home-page: https://github.com/eigenvivek/DiffDRR
Author: Vivek Gopalakrishnan
Author-email: vivekg@mit.edu
License: MIT License
Keywords: nbdev jupyter notebook python
Classifier: Development Status :: 4 - Beta
Classifier: Intended Audience :: Developers
Classifier: Natural Language :: English
Classifier: Programming Language :: Python :: 3.8
Classifier: Programming Language :: Python :: 3.9
Classifier: Programming Language :: Python :: 3.10
Classifier: Programming Language :: Python :: 3.11
Classifier: License :: OSI Approved :: MIT License
Requires-Python: >=3.8
License-File: LICENSE
Requires-Dist: matplotlib
Requires-Dist: seaborn
Requires-Dist: tqdm
Requires-Dist: imageio
Requires-Dist: fastcore
Requires-Dist: pyvista[all]
Requires-Dist: einops
Requires-Dist: torchvision
Requires-Dist: scipy
Requires-Dist: torchio
Requires-Dist: timm
Requires-Dist: numpy
Requires-Dist: kornia
Requires-Dist: torch
Provides-Extra: dev
Requires-Dist: nbdev ; extra == 'dev'
Requires-Dist: black ; extra == 'dev'
Requires-Dist: flake8 ; extra == 'dev'
Requires-Dist: ipykernel ; extra == 'dev'
Requires-Dist: ipywidgets ; extra == 'dev'
Requires-Dist: jupyterlab ; extra == 'dev'
Requires-Dist: jupyterlab-execute-time ; extra == 'dev'
Requires-Dist: jupyterlab-code-formatter ; extra == 'dev'
Requires-Dist: isort ; extra == 'dev'
